aliyunsdkes_serverless/__init__.py
aliyunsdkes_serverless/request/__init__.py
aliyunsdkes_serverless/request/v20220822/CreateAppRequest.py
aliyunsdkes_serverless/request/v20220822/CreateDataStreamRequest.py
aliyunsdkes_serverless/request/v20220822/DeleteAccessTokenRequest.py
aliyunsdkes_serverless/request/v20220822/DeleteAppRequest.py
aliyunsdkes_serverless/request/v20220822/DeleteDataStreamRequest.py
aliyunsdkes_serverless/request/v20220822/DescibeRegionsRequest.py
aliyunsdkes_serverless/request/v20220822/DisableAccessTokenRequest.py
aliyunsdkes_serverless/request/v20220822/EnableAccessTokenRequest.py
aliyunsdkes_serverless/request/v20220822/GenerateAcccessTokenRequest.py
aliyunsdkes_serverless/request/v20220822/GetAppRequest.py
aliyunsdkes_serverless/request/v20220822/GetDataStreamRequest.py
aliyunsdkes_serverless/request/v20220822/GetRegionInfoRequest.py
aliyunsdkes_serverless/request/v20220822/ListAccessTokensRequest.py
aliyunsdkes_serverless/request/v20220822/ListAppsRequest.py
aliyunsdkes_serverless/request/v20220822/ListDataStreamsRequest.py
aliyunsdkes_serverless/request/v20220822/UpdateAppRequest.py
aliyunsdkes_serverless/request/v20220822/UpdateDataStreamRequest.py
aliyunsdkes_serverless/request/v20220822/__init__.py
aliyun_python_sdk_es_serverless-1.0.0.dist-info/LICENSE
aliyun_python_sdk_es_serverless-1.0.0.dist-info/METADATA
aliyun_python_sdk_es_serverless-1.0.0.dist-info/WHEEL
aliyun_python_sdk_es_serverless-1.0.0.dist-info/top_level.txt
aliyun_python_sdk_es_serverless-1.0.0.dist-info/RECORD
